<?xml version="1.0" encoding="UTF-8"?>
<LanguageData>
  
  <!-- EN:
    <li>questDescription->[asker_nameFull], [asker_faction_leaderTitle] of [asker_faction_name], has sent us a message. Apparently, [siteFaction_pawnsPlural] are resting with their beasts before continuing their journey.\n            \n[asker_nameDef] gave us their location, if we want to, we can go attack them.</li>
  -->
  <VFES_CaravanRaid.questDescriptionRules.rulesStrings>[asker_faction_name]的[asker_faction_leaderTitle][asker_nameFull]向我們透露了一條消息。看起來，旅途中的[siteFaction_pawnsPlural]與他們的馱運動物正在我們附近的某處停歇。\n[asker_nameDef]告訴了我們這支商隊的落腳處，或許可以打他們一個措手不及。</VFES_CaravanRaid.questDescriptionRules.rulesStrings>
  <!-- EN:
    <li>questName->Caravan [raid]</li>
    <li>questName->[asker_nameDef] and the Caravan [raid]</li>
    <li>raid->Raid</li>
    <li>raid->Attack</li>
    <li>raid->Ambush</li>
  -->
  <VFES_CaravanRaid.questNameRules.rulesStrings>  
    <li>questName->[raid]商隊</li>
    <li>questName->[asker_nameDef]的[raid]商隊機會</li>
    <li>raid->襲擊</li>
    <li>raid->攻擊</li>
    <li>raid->伏擊</li>
  </VFES_CaravanRaid.questNameRules.rulesStrings>
  <!-- EN: Quest expired: [resolvedQuestName] -->
  <VFES_CaravanRaid.root.nodes.WorldObjectTimeout.node.nodes.Letter.label.slateRef>任務已失效：[resolvedQuestName]</VFES_CaravanRaid.root.nodes.WorldObjectTimeout.node.nodes.Letter.label.slateRef>
  <!-- EN: The [siteFaction_pawnsPlural] packed up their stuff and moved on. The quest [resolvedQuestName] has expired. -->
  <VFES_CaravanRaid.root.nodes.WorldObjectTimeout.node.nodes.Letter.text.slateRef>[siteFaction_pawnsPlural]已經收拾好了他們的物資，繼續前進了。任務[resolvedQuestName]已失效。</VFES_CaravanRaid.root.nodes.WorldObjectTimeout.node.nodes.Letter.text.slateRef>
  <!-- EN: Quest failed: [resolvedQuestName] -->
  <VFES_CaravanRaid.root.nodes.siteDestroyed.node.nodes.Letter.label.slateRef>任務失敗：[resolvedQuestName]</VFES_CaravanRaid.root.nodes.siteDestroyed.node.nodes.Letter.label.slateRef>
  <!-- EN: After being discovered, the [siteFaction_pawnsPlural] left. The quest [resolvedQuestName] has ended. -->
  <VFES_CaravanRaid.root.nodes.siteDestroyed.node.nodes.Letter.text.slateRef>在被發現後，[siteFaction_pawnsPlural]離開了。任務[resolvedQuestName]已失效。</VFES_CaravanRaid.root.nodes.siteDestroyed.node.nodes.Letter.text.slateRef>
  
  <!-- EN:
    <li>questName->Bounty: [nameFull] [nickname]</li>
    <li>questName->Wanted, Dead or Alive: [nickname]</li>
    <li>questName->[nickname]'s brigands</li>
    <li>questDescription->[asker_nameFull], [asker_faction_leaderTitle] of [asker_faction_name] hails us. Apparently, the notorious [criminal_nameFull] of [siteFaction_name] is hiding out in our vicinity.\n\n[asker_nameDef] is asking us to bring [nickname] to one of their settlements for a grand sum of [bounty] silver, double if alive. They are hiding in a safe house and it's probably guarded.\n\nIf we clear out their camp, [allRewardsDescriptions]</li>
  -->
  <VFES_Wanted.questDescriptionAndNameRules.rulesStrings>  
    <li>questName->懸賞：[nameFull][nickname]</li>
    <li>questName->通緝[nickname]：不論死活</li>
    <li>questName->緝拿[nickname]</li>
    <li>questDescription->[asker_faction_name]的[asker_faction_leaderTitle][asker_nameFull]呼叫了我們。看起來，[siteFaction_name]臭名昭著的[criminal_nameFull]正躲在我們附近。\n\n[asker_nameDef]要求我們將[nickname]帶至他們的一個定居點。作為報酬，他們會支付賞金[bounty]銀，如果目標活著則翻倍。[nickname]躲在一個安全屋裡，且可能有護衛存在。\n\n如果我們能成功摧毀[nickname]的藏身處，[allRewardsDescriptions]</li>
  </VFES_Wanted.questDescriptionAndNameRules.rulesStrings>
  <!-- EN: Quest expired: [resolvedQuestName] -->
  <VFES_Wanted.root.nodes.WorldObjectTimeout.node.nodes.Letter.label.slateRef>任務已失效：[resolvedQuestName]</VFES_Wanted.root.nodes.WorldObjectTimeout.node.nodes.Letter.label.slateRef>
  <!-- EN: [criminal_nameFull] heard about their compromised position thus have decided to leave the area. The quest [resolvedQuestName] has expired. -->
  <VFES_Wanted.root.nodes.WorldObjectTimeout.node.nodes.Letter.text.slateRef>[criminal_nameFull]聽聞自己的位置暴露了，決定離開此地。任務[resolvedQuestName]已失效。</VFES_Wanted.root.nodes.WorldObjectTimeout.node.nodes.Letter.text.slateRef>
  <!-- EN: Quest failed: [resolvedQuestName] -->
  <VFES_Wanted.root.nodes.siteDestroyed.node.nodes.Letter.label.slateRef>任務失敗：[resolvedQuestName]</VFES_Wanted.root.nodes.siteDestroyed.node.nodes.Letter.label.slateRef>
  <!-- EN: The brigands has packed up and moved on. -->
  <VFES_Wanted.root.nodes.siteDestroyed.node.nodes.Letter.text.slateRef>匪徒們已經收拾好東西，繼續前進了。</VFES_Wanted.root.nodes.siteDestroyed.node.nodes.Letter.text.slateRef>
  <!-- EN: Payment arrived -->
  <VFES_Wanted.root.nodes.siteAllEnemiesDefeated.node.customLetterLabel.slateRef>獎勵已送達</VFES_Wanted.root.nodes.siteAllEnemiesDefeated.node.customLetterLabel.slateRef>
  <!-- EN: You have defeated [criminal_nameFull] and eliminated the camp!\n\nThe bonus reward from [asker_faction_name] has arrived. -->
  <VFES_Wanted.root.nodes.siteAllEnemiesDefeated.node.customLetterText.slateRef>你成功擊敗了[criminal_nameFull]，並摧毀了藏身處！\n\n來自[asker_faction_name]的獎賞已經抵達。</VFES_Wanted.root.nodes.siteAllEnemiesDefeated.node.customLetterText.slateRef>
  
</LanguageData>