<?xml version="1.0" encoding="UTF-8"?>
<LanguageData>
  
  <!-- EN: balaclava -->
  <VAE_Headgear_Balaclava.label>巴拉克拉瓦头套</VAE_Headgear_Balaclava.label>
  <!-- EN: A full face textile mask. Hides the identity of the wearer while providing warmth. -->
  <VAE_Headgear_Balaclava.description>用织物制成的全覆式面罩，能遮挡穿戴者的面部神态，使得难以被解读和预测。</VAE_Headgear_Balaclava.description>
  
  <!-- EN: ghillie hood -->
  <VAE_Headgear_GhillieHood.label>吉利兜帽</VAE_Headgear_GhillieHood.label>
  <!-- EN: A camouflage hood designed to resemble the environment. Gives user more time to aim precisely, but provides little to no defence. -->
  <VAE_Headgear_GhillieHood.description>能融入环境的伪装用兜帽。它可以让射手在被发现前拥有更多的瞄准时间，但防护能力较差。</VAE_Headgear_GhillieHood.description>
  
  <!-- EN: HAZMAT hood -->
  <VAE_Headgear_HAZMATMask.label>生化防护头罩</VAE_Headgear_HAZMATMask.label>
  <!-- EN: A full head gas mask, which alongside the HAZMAT suit provides a full protection from toxic and psychic effects. -->
  <VAE_Headgear_HAZMATMask.description>与生化防护服配套的全覆式头罩，能有效防止毒素、辐射和心灵攻击的侵害，但无法抵挡子弹和近战攻击。\n\n由于裹得过分严实，会降低穿戴者的全局工作速度。</VAE_Headgear_HAZMATMask.description>
  
</LanguageData>