<?xml version="1.0" encoding="UTF-8"?>
<LanguageData>
  
  <!-- EN: cyclone rapid burst -->
  <VWEB_CycloneRapidBurst.label>弹雨倾泻</VWEB_CycloneRapidBurst.label>
  <!-- EN: Fire a rapid volley of shots by utilising the bioferrite-accelerated engine. -->
  <VWEB_CycloneRapidBurst.description>启动活铁过载引擎，以极快的速度向前方倾泻弹雨。</VWEB_CycloneRapidBurst.description>
  
  <!-- EN: firestorm blazer -->
  <VWEB_FirestormBlazer.label>爆焰喷射</VWEB_FirestormBlazer.label>
  <!-- EN: Fire a short-ranged flame blast over a short but wide area. -->
  <VWEB_FirestormBlazer.description>对装填的活铁加压，使用附挂燃爆器喷射出一片短距离火焰。</VWEB_FirestormBlazer.description>
  
  <!-- EN: flarestrike flare -->
  <VWEB_FlarestrikeFlare.label>眩光照明弹</VWEB_FlarestrikeFlare.label>
  <!-- EN: Expend a pressurized bioferrite charge to create a burst of flame. -->
  <VWEB_FlarestrikeFlare.description>向目标点处发射眩光照明弹。</VWEB_FlarestrikeFlare.description>
  
</LanguageData>