<?xml version="1.0" encoding="UTF-8"?>
<LanguageData>
  
  <!-- EN: panic-fleeing light -->
  <VRE_Photophobia.label>逃离光源</VRE_Photophobia.label>
  <!-- EN: Mental state: Fleeing the light -->
  <VRE_Photophobia.baseInspectLine>精神状态：逃离光源</VRE_Photophobia.baseInspectLine>
  <!-- EN: {0} is fleeing the light. -->
  <VRE_Photophobia.beginLetter>{0}正在逃离光源。</VRE_Photophobia.beginLetter>
  <!-- EN: fleeing light -->
  <VRE_Photophobia.beginLetterLabel>逃离光源</VRE_Photophobia.beginLetterLabel>
  <!-- EN: {0} is no longer fleeing the light. -->
  <VRE_Photophobia.recoveryMessage>{0}不再逃离光源。</VRE_Photophobia.recoveryMessage>
  
</LanguageData>